tests/__init__.py
tests/test_cache.py
tests/test_registry.py
tests/test_serializers.py
tests/prefect/__init__.py
tests/prefect/test_result.py
xpersist/__init__.py
xpersist/cache.py
xpersist/registry.py
xpersist/serializers.py
xpersist/prefect/__init__.py
xpersist/prefect/result.py
xpersist-2021.12.17.dist-info/LICENSE
xpersist-2021.12.17.dist-info/METADATA
xpersist-2021.12.17.dist-info/WHEEL
xpersist-2021.12.17.dist-info/top_level.txt
xpersist-2021.12.17.dist-info/RECORD
