Metadata-Version: 2.1
Name: xpersist
Version: 2021.12.17
Summary: xpersist provides custom caching utility functions in Python
Home-page: https://github.com/NCAR/xpersist
Maintainer: Xdev
Maintainer-email: xdev@ucar.edu
License: Apache Software License 2.0
Project-URL: Documentation, https://github.com/NCAR/xpersist
Project-URL: Source, https://github.com/NCAR/xpersist
Project-URL: Tracker, https://github.com/NCAR/xpersist/issues
Platform: UNKNOWN
Classifier: Development Status :: 2 - Pre-Alpha
Classifier: License :: OSI Approved :: Apache Software License
Classifier: Natural Language :: English
Classifier: Programming Language :: Python :: 3
Classifier: Programming Language :: Python :: 3.7
Classifier: Programming Language :: Python :: 3.8
Classifier: Programming Language :: Python :: 3.9
Classifier: Topic :: Scientific/Engineering
Classifier: Operating System :: OS Independent
Classifier: Intended Audience :: Science/Research
Requires-Python: >=3.7
License-File: LICENSE
Requires-Dist: xarray
Requires-Dist: zarr
Requires-Dist: netcdf4
Requires-Dist: pydantic
Requires-Dist: catalogue
Requires-Dist: fsspec
Requires-Dist: joblib
Requires-Dist: prefect (<2.0,>=0.15.9)
Requires-Dist: xcollection
